pauli_tracker-0.1.3.dist-info/METADATA
pauli_tracker-0.1.3.dist-info/WHEEL
pauli_tracker-0.1.3.dist-info/licenses/LICENSE-APACHE
pauli_tracker-0.1.3.dist-info/licenses/LICENSE-MIT
pauli_tracker/live/map.py
pauli_tracker/live/__init__.py
pauli_tracker/live/vec.py
pauli_tracker/pauli.py
pauli_tracker/__init__.py
pauli_tracker/frames/map.py
pauli_tracker/frames/__init__.py
pauli_tracker/frames/vec.py
pauli_tracker/_lib.cpython-310-x86_64-linux-gnu.so
pauli_tracker-0.1.3.dist-info/RECORD
