Metadata-Version: 2.3
Name: pauli_tracker
Version: 0.1.3
Classifier: License :: OSI Approved :: MIT License
Classifier: License :: OSI Approved :: Apache Software License
License-File: LICENSE-APACHE
License-File: LICENSE-MIT
Summary: A library to track Pauli gates through Clifford circuits.
Keywords: quantum,clifford,pauli,mbqc
Author: Jannis Ruh <ruh.j81@gmail.com>
Author-email: Jannis Ruh <ruh.j81@gmail.com>
License: MIT OR Apache-2.0
Requires-Python: >=3.8
Project-URL: Repository, https://github.com/taeruh/pauli_tracker
Project-URL: Documentation, https://taeruh.github.io/pauli_tracker/
